ANU_inversion_course-0.1.1.data/data/bin/_rjmcmc.cp38-win_amd64.pyd
ANU_inversion_course-0.1.1.data/data/lib/_rjmcmc.lib
anu_inversion_course/__init__.py
anu_inversion_course/_rfc.cp38-win_amd64.pyd
anu_inversion_course/curveFitting.py
anu_inversion_course/eqlocate.py
anu_inversion_course/gaussian_corner.py
anu_inversion_course/plotcovellipse.py
anu_inversion_course/rayTracer.py
anu_inversion_course/rejectmethod.py
anu_inversion_course/rf.py
anu_inversion_course/rjmcmc.py
anu_inversion_course/xrayTomography.py
ANU_inversion_course-0.1.1.dist-info/METADATA
ANU_inversion_course-0.1.1.dist-info/WHEEL
ANU_inversion_course-0.1.1.dist-info/top_level.txt
ANU_inversion_course-0.1.1.dist-info/zip-safe
ANU_inversion_course-0.1.1.dist-info/RECORD
