Metadata-Version: 2.1
Name: ANU_inversion_course
Version: 0.1.1
Summary: ANU Inversion Course Package
Author: InLab
Keywords: inversion,inference,geoscience,geophysics
Classifier: Development Status :: 3 - Alpha
Classifier: Intended Audience :: Education
Classifier: Intended Audience :: Science/Research
Classifier: Programming Language :: Python
Classifier: Programming Language :: Python :: 3
Classifier: Programming Language :: Python :: 3.8
Classifier: Programming Language :: Python :: 3.9
Classifier: Programming Language :: Python :: 3.10
Classifier: Programming Language :: Python :: Implementation :: CPython
Classifier: Topic :: Scientific/Engineering :: Physics
Requires-Python: >=3.6
Requires-Dist: numpy >=1.18
Requires-Dist: scipy >=1.0.0
Requires-Dist: tqdm >=4.62.0
Requires-Dist: seaborn >=0.11.0
Requires-Dist: corner
